oca_ds_validator/__init__.py
oca_ds_validator/oca_ds_validator.py
oca_ds_validator-0.0.2.dist-info/METADATA
oca_ds_validator-0.0.2.dist-info/WHEEL
oca_ds_validator-0.0.2.dist-info/licenses/LICENSE
oca_ds_validator-0.0.2.dist-info/RECORD
