Metadata-Version: 2.1
Name: oca_ds_validator
Version: 0.0.2
Summary: Validate OCA dataset in python workflows
Project-URL: Homepage, https://github.com/agrifooddatacanada/OCA_data_set_validator
Project-URL: Issues, https://github.com/agrifooddatacanada/OCA_data_set_validator/issues
Author: Xingjian Xu and Steven Mugisha Mizero
License-File: LICENSE
Keywords: Data Entry,OCA JSON Bundle
Classifier: License :: OSI Approved :: European Union Public Licence 1.2 (EUPL 1.2)
Classifier: Operating System :: OS Independent
Classifier: Programming Language :: Python :: 3
Requires-Python: >=3.8
